melektrodica/__init__.py
melektrodica/calculator.py
melektrodica/collector.py
melektrodica/constants.py
melektrodica/coordinator.py
melektrodica/fitter.py
melektrodica/grapher.py
melektrodica/kpynetic.py
melektrodica/tester.py
melektrodica/tools.py
melektrodica/writer.py
melektrodica-1.0.0.dist-info/LICENSE
melektrodica-1.0.0.dist-info/METADATA
melektrodica-1.0.0.dist-info/WHEEL
melektrodica-1.0.0.dist-info/top_level.txt
melektrodica-1.0.0.dist-info/RECORD
