Metadata-Version: 2.2
Name: melektrodica
Version: 1.0.0
Summary: A Python Electrochemistry Toolbox for Modeling Microkinetic Electrocatalytic Reactions
Author: C. Baqueiro Basto, M. Secanell, L.C. Ordoñez
Author-email: carlosbaqueirob@gmail.com
License: CC BY-NC-SA 4.0
Classifier: Programming Language :: Python :: 3
Classifier: License :: OSI Approved :: MIT License
Classifier: Operating System :: OS Independent
Requires-Python: >=3.6
License-File: LICENSE
Requires-Dist: pytest
Requires-Dist: scipy
Requires-Dist: numpy
Requires-Dist: pandas
Requires-Dist: matplotlib
Requires-Dist: networkx
Requires-Dist: colorlog
Requires-Dist: tabulate
Requires-Dist: IPython
Dynamic: author
Dynamic: author-email
Dynamic: classifier
Dynamic: description
Dynamic: description-content-type
Dynamic: license
Dynamic: requires-dist
Dynamic: requires-python
Dynamic: summary
